valdemarcord/__init__.py
valdemarcord/discord.py
valdemarcord-1.1.2.dist-info/METADATA
valdemarcord-1.1.2.dist-info/WHEEL
valdemarcord-1.1.2.dist-info/top_level.txt
valdemarcord-1.1.2.dist-info/RECORD
