Metadata-Version: 2.2
Name: valdemarcord
Version: 1.1.2
Summary: discord api wrapper (beta)
Author: valdemarkid
Requires-Python: >=3.6
Requires-Dist: requests
Requires-Dist: beautifulsoup4
Requires-Dist: orjson
Requires-Dist: websocket-client
Dynamic: author
Dynamic: description
Dynamic: description-content-type
Dynamic: requires-dist
Dynamic: requires-python
Dynamic: summary
